trilium_alchemy/__init__.py
trilium_alchemy/core/__init__.py
trilium_alchemy/core/attribute/__init__.py
trilium_alchemy/core/attribute/attribute.py
trilium_alchemy/core/attribute/label.py
trilium_alchemy/core/attribute/relation.py
trilium_alchemy/core/branch/__init__.py
trilium_alchemy/core/branch/branch.py
trilium_alchemy/core/cache.py
trilium_alchemy/core/declarative/__init__.py
trilium_alchemy/core/declarative/base.py
trilium_alchemy/core/declarative/decorators.py
trilium_alchemy/core/entity/__init__.py
trilium_alchemy/core/entity/entity.py
trilium_alchemy/core/entity/model.py
trilium_alchemy/core/entity/types.py
trilium_alchemy/core/exceptions.py
trilium_alchemy/core/note/__init__.py
trilium_alchemy/core/note/attributes/__init__.py
trilium_alchemy/core/note/attributes/_filters.py
trilium_alchemy/core/note/attributes/attributes.py
trilium_alchemy/core/note/attributes/labels.py
trilium_alchemy/core/note/attributes/relations.py
trilium_alchemy/core/note/branches.py
trilium_alchemy/core/note/content.py
trilium_alchemy/core/note/extension.py
trilium_alchemy/core/note/model.py
trilium_alchemy/core/note/note.py
trilium_alchemy/core/session.py
trilium_alchemy/core/utils.py
trilium_alchemy/lib/__init__.py
trilium_alchemy/lib/assets/system.css
trilium_alchemy/lib/extension_types.py
trilium_alchemy/lib/note_types.py
trilium_alchemy/lib/system_types.py
trilium_alchemy/tools/cli/_utils.py
trilium_alchemy/tools/cli/db.py
trilium_alchemy/tools/cli/fs.py
trilium_alchemy/tools/cli/main.py
trilium_alchemy/tools/cli/note.py
trilium_alchemy/tools/cli/test.py
trilium_alchemy/tools/cli/tree.py
trilium_alchemy/tools/config.py
trilium_alchemy/tools/fs/meta.py
trilium_alchemy/tools/fs/note.py
trilium_alchemy/tools/fs/tree.py
trilium_alchemy/tools/utils.py
trilium_alchemy/tools/yaml_model.py
trilium_alchemy-0.7.0.dist-info/LICENSE
trilium_alchemy-0.7.0.dist-info/METADATA
trilium_alchemy-0.7.0.dist-info/WHEEL
trilium_alchemy-0.7.0.dist-info/entry_points.txt
trilium_alchemy-0.7.0.dist-info/RECORD
